dynaroute_mcp_server/__init__.py
dynaroute_mcp_server/cli.py
dynaroute_mcp_server/server.py
dynaroute_mcp_server-1.0.2.dist-info/licenses/LICENSE
dynaroute_mcp_server-1.0.2.dist-info/METADATA
dynaroute_mcp_server-1.0.2.dist-info/WHEEL
dynaroute_mcp_server-1.0.2.dist-info/entry_points.txt
dynaroute_mcp_server-1.0.2.dist-info/top_level.txt
dynaroute_mcp_server-1.0.2.dist-info/RECORD
