Metadata-Version: 2.4
Name: dynaroute-mcp-server
Version: 1.0.2
Summary: MCP server for DynaRoute - intelligent chat completions with automatic model routing and cost optimization
Author-email: Mohammed Abraar <abraar237@gmail.com>
License: MIT
Project-URL: Homepage, https://github.com/abraar237/dynaroute-mcp-server
Project-URL: Repository, https://github.com/abraar237/dynaroute-mcp-server
Project-URL: Issues, https://github.com/abraar237/dynaroute-mcp-server/issues
Project-URL: Documentation, https://github.com/abraar237/dynaroute-mcp-server#readme
Keywords: mcp,dynaroute,ai,llm,cost-optimization,model-routing
Classifier: Development Status :: 4 - Beta
Classifier: Intended Audience :: Developers
Classifier: License :: OSI Approved :: MIT License
Classifier: Operating System :: OS Independent
Classifier: Programming Language :: Python :: 3
Classifier: Programming Language :: Python :: 3.8
Classifier: Programming Language :: Python :: 3.9
Classifier: Programming Language :: Python :: 3.10
Classifier: Programming Language :: Python :: 3.11
Classifier: Programming Language :: Python :: 3.12
Classifier: Topic :: Software Development :: Libraries :: Python Modules
Classifier: Topic :: Scientific/Engineering :: Artificial Intelligence
Requires-Python: >=3.8
License-File: LICENSE
Requires-Dist: mcp>=1.0.0
Requires-Dist: dynaroute-client>=1.0.2
Provides-Extra: dev
Requires-Dist: pytest>=7.0.0; extra == "dev"
Requires-Dist: pytest-asyncio>=0.21.0; extra == "dev"
Requires-Dist: black>=23.0.0; extra == "dev"
Requires-Dist: isort>=5.0.0; extra == "dev"
Requires-Dist: flake8>=6.0.0; extra == "dev"
Dynamic: license-file
